tennis/GTF.py
tennis/__init__.py
tennis/main.py
tennis/phylogenTreeSolver.py
tennis/random_iterator_product.py
tennis/tennis.py
tennis/util.py
tennis_transcriptome-0.0.1.dist-info/METADATA
tennis_transcriptome-0.0.1.dist-info/WHEEL
tennis_transcriptome-0.0.1.dist-info/entry_points.txt
tennis_transcriptome-0.0.1.dist-info/licenses/LICENSE
tennis_transcriptome-0.0.1.dist-info/RECORD
