Metadata-Version: 2.3
Name: tennis-transcriptome
Version: 0.0.1
Summary: TENNIS is an evolution-based model to predict unannotated isoforms and refine existing transcriptome annotations
Project-URL: Homepage, https://github.com/Shao-Group/TENNIS/
Project-URL: Bug Tracker, https://github.com/Shao-Group/TENNIS/issues
Author-email: Xiaofei Carl Zang <xbz5174@psu.edu>, Ke Chen <kxc5915@psu.edu>, Mingfu Shao <mxs2589@psu.edu>
License-Expression: BSD-3-Clause
License-File: LICENSE
Classifier: License :: OSI Approved :: BSD License
Classifier: Programming Language :: Python :: 3
Requires-Python: >=3.7
Requires-Dist: python-sat[aiger,approxmc,cryptosat,pblib]>=0.1.8.dev3
